{
  "id": "loup_garou",
  "name": "Loup-Garou",
  "class": "corvette",
  "chassis_archetype": "saucer",
  "description": "A mid-bulk mining corvette. Blunt, utilitarian frame with the cockpit forward and slightly elevated. Argosy-class profile — workhorse, not warship. Heavily modified: extra hardpoints welded onto former mining laser mounts, patch armor, a shuttle grafted aft that the original designer never intended.",
  "origin": "reach",
  "customization_tier": "high",
  "stats": {
    "mass": 280,
    "armor": 3,
    "crew_capacity": 8,
    "cargo_capacity": 40,
    "jump_drive_capable": true
  },
  "flight": {
    "top_speed": 44,
    "acceleration": 26,
    "turn_rate": 1.5,
    "boost_multiplier": 2.4,
    "drift": 0.5,
    "bank_angle_deg": 42
  },
  "hardpoints": {
    "weapons": 4,
    "utilities": 3,
    "engines": 2
  },
  "interior_rooms": ["cockpit", "bridge", "engineering", "med_bay", "galley", "crew_quarters", "cargo_hold", "cryo", "airlock"],
  "room_zones": {
    "cockpit": "#2a5a8a",
    "bridge": "#1a4a7a",
    "engineering": "#aa6020",
    "med_bay": "#d8dde0",
    "galley": "#6a7a3a",
    "crew_quarters": "#4a4a6a",
    "cargo_hold": "#5a5030",
    "cryo": "#5a7a8a",
    "airlock": "#5a5a6a"
  },
  "stations": [
    { "id": "pilot", "name": "Pilot Console", "room": "cockpit" },
    { "id": "weapons", "name": "Weapons Station", "room": "bridge" },
    { "id": "scanner", "name": "Scanner Array", "room": "bridge" },
    { "id": "engineering", "name": "Engineering Console", "room": "engineering" },
    { "id": "cargo", "name": "Cargo Terminal", "room": "cargo_hold" },
    { "id": "cryopod", "name": "Cryopod", "room": "cryo" }
  ],
  "interior_layout": {
    "cols": 3,
    "rows": 3,
    "grid": [
      ["cockpit", "bridge", "airlock"],
      ["crew_quarters", "galley", "med_bay"],
      ["cryo", "engineering", "cargo_hold"]
    ]
  },
  "attached": ["loup_garou_shuttle"]
}
